README.md
setup.py
DistanceControl/__init__.py
distancecontrol.egg-info/PKG-INFO
distancecontrol.egg-info/SOURCES.txt
distancecontrol.egg-info/dependency_links.txt
distancecontrol.egg-info/requires.txt
distancecontrol.egg-info/top_level.txt