Metadata-Version: 2.1
Name: distancecontrol
Version: 0.0.1
Summary: A library used to control programs(mainly games) without focusing them.
Home-page: http://flafy.herokuapp.com/
Author: Flafy Arazi
Author-email: flafyarazi@gmail.com
License: MIT
Keywords: control send keys game program without focus active top topmost SendMessage PostMessage
Platform: UNKNOWN
Classifier: Development Status :: 5 - Production/Stable
Classifier: Intended Audience :: Education
Classifier: Operating System :: Microsoft :: Windows :: Windows 10
Classifier: License :: OSI Approved :: MIT License
Classifier: Programming Language :: Python :: 3
